CHANGES
LICENSE
MANIFEST.in
README.rst
TODO
requirements-tox.txt
requirements.txt
setup.cfg
setup.py
docs/Makefile
docs/code.rst
docs/conf.py
docs/index.rst
docs/make.bat
docs/requirements.txt
docs/_build/doctrees/code.doctree
docs/_build/doctrees/environment.pickle
docs/_build/doctrees/index.doctree
docs/_build/doctrees/code/collections.doctree
docs/_build/doctrees/code/crypto.doctree
docs/_build/doctrees/code/dev.doctree
docs/_build/doctrees/code/fs.doctree
docs/_build/doctrees/code/http.doctree
docs/_build/doctrees/code/image.doctree
docs/_build/doctrees/code/math.doctree
docs/_build/doctrees/code/mixins.doctree
docs/_build/doctrees/code/text.doctree
docs/_build/doctrees/code/time.doctree
docs/_build/doctrees/code/ui.doctree
docs/_build/html/.buildinfo
docs/_build/html/code.html
docs/_build/html/genindex.html
docs/_build/html/index.html
docs/_build/html/objects.inv
docs/_build/html/py-modindex.html
docs/_build/html/search.html
docs/_build/html/searchindex.js
docs/_build/html/_modules/index.html
docs/_build/html/_modules/py_utilities/collections/collections_utilities.html
docs/_build/html/_modules/py_utilities/dev/command_line_utilities.html
docs/_build/html/_modules/py_utilities/fs/file_utilities.html
docs/_build/html/_modules/py_utilities/fs/fs_utilities.html
docs/_build/html/_modules/py_utilities/fs/path_utilities.html
docs/_build/html/_modules/py_utilities/image/image_utilities.html
docs/_build/html/_modules/py_utilities/math/math_utilities.html
docs/_build/html/_modules/py_utilities/text/csv_utilities.html
docs/_build/html/_modules/py_utilities/text/string_utilities.html
docs/_build/html/_modules/py_utilities/text/text_utilities.html
docs/_build/html/_modules/py_utilities/time/date_utilities.html
docs/_build/html/_modules/py_utilities/ui/color_utilities.html
docs/_build/html/_sources/code.txt
docs/_build/html/_sources/index.txt
docs/_build/html/_sources/code/collections.txt
docs/_build/html/_sources/code/crypto.txt
docs/_build/html/_sources/code/dev.txt
py_utilities.egg-info/PKG-INFO
py_utilities.egg-info/SOURCES.txt
py_utilities.egg-info/dependency_links.txt
py_utilities.egg-info/requires.txt
py_utilities.egg-info/top_level.txt
