Metadata-Version: 1.1
Name: py-utilities
Version: 0.0.3
Summary: Collection of python utilities
Home-page: https://github.com/ryankanno/py-utilities
Author: Ryan Kanno
Author-email: ryankanno@localkinegrinds.com
License: MIT
Platform: UNKNOWN
Classifier: Development Status :: 3 - Alpha
Classifier: Intended Audience :: Developers
Classifier: Programming Language :: Python
Classifier: License :: OSI Approved :: MIT License
Classifier: Topic :: Utilities
